{
  "type": "FeatureCollection", 
  "features": [
    {
      "geometry": {
        "type": "Point", 
        "coordinates": [
          -149.9093484, 
          61.1946237
        ]
      }, 
      "layer": "US", 
      "type": "Feature", 
      "properties": {
        "description": "http://www.anchoragegoclub.com/ , Title Wave books\r\n1360 West Northern Lights Blvd , Thursday 7:30\r\nSaturday 5:00 pm-9:00 pm , Robert E. Stoller stoller@alaska.net\r\n907-522-2299", 
        "name": "Anchorage Go Club"
      }
    }, 
    {
      "geometry": {
        "type": "Point", 
        "coordinates": [
          -111.9205551, 
          33.4187288
        ]
      }, 
      "layer": "US", 
      "type": "Feature", 
      "properties": {
        "description": "http://azgoclub.org/ , Arizona State University Memorial Union, 301 E. Orange St., Tempe on the ground floor (in the southeast section of the building in the raised dining area near the Taco Bell). , Saturday 1PM , William Gundberg bill@azgoclub.org 480-831-5567 H 480-429-0300 W", 
        "name": "Arizona Go Club Tempe - Saturday"
      }
    }, 
    {
      "geometry": {
        "type": "Point", 
        "coordinates": [
          -111.926202661538, 
          33.4231647384615
        ]
      }, 
      "layer": "US", 
      "type": "Feature", 
      "properties": {
        "description": "http://azgoclub.org/ , IHOP, Corner of Rural and University - 705 S Rural Road, Tempe , Tuesday 7PM , William Gundberg bill@azgoclub.org\r\n480-831-5567 H\r\n480-429-0300 W", 
        "name": "Arizona Go Club Tempe - Tuesday"
      }
    }, 
    {
      "geometry": {
        "type": "Point", 
        "coordinates": [
          -122.268072077, 
          37.8701935782
        ]
      }, 
      "layer": "US", 
      "type": "Feature", 
      "properties": {
        "description": "http://www.berkeleygoclub.org/ , Berkeley Go Club Clubroom: 2161 Shattuck Avenue (at Center), 2nd floor, Suite 222 , Fridays 6:00 PM - 9:00 PM\r\nSaturdays: 2:00 pm onward\r\nSundays: 2:00 pm onward\r\nCall 510-501-8314 to be let in if front door is locked.", 
        "name": "Berkeley Go Club"
      }
    }, 
    {
      "geometry": {
        "type": "Point", 
        "coordinates": [
          -86.8284003, 
          33.3620295
        ]
      }, 
      "layer": "US", 
      "type": "Feature", 
      "properties": {
        "description": "We play at different places around the Hoover area. , Louis Gutenschwager <louis@bhamgo.org> 205-903-0688", 
        "name": "Birmingham Go Association"
      }
    }, 
    {
      "geometry": {
        "type": "Point", 
        "coordinates": [
          -90.131136, 
          29.948106
        ]
      }, 
      "layer": "US", 
      "type": "Feature", 
      "properties": {
        "description": "https://www.facebook.com/Cranes-Nest-GO-Club-140027432709789/ , Z'otz Cafe, 8210 Oak St, New Orleans, LA , Wednesdays, 6-10pm", 
        "name": "Crane's Nest Go Club"
      }
    }, 
    {
      "geometry": {
        "type": "Point", 
        "coordinates": [
          -96.764634, 
          33.002104
        ]
      }, 
      "layer": "US", 
      "type": "Feature", 
      "properties": {
        "description": "http://dallasgoclub.org , 320 Coit Rd, Plano, TX 75075 , Thursdays 5-10pm , dallasgo@gmail.com", 
        "name": "Dallas Go Club"
      }
    }, 
    {
      "geometry": {
        "type": "Point", 
        "coordinates": [
          -121.740198756529, 
          38.5453527
        ]
      }, 
      "layer": "US", 
      "type": "Feature", 
      "properties": {
        "description": "http://www.davissacramentogoclub.org/ , Steve's Pizza, 314 F Street, Davis, CA , Thursdays: 6:00 pm to 10:00 pm", 
        "name": "Davis Go Club"
      }
    }, 
    {
      "geometry": {
        "type": "Point", 
        "coordinates": [
          -87.682056427, 
          42.048798689
        ]
      }, 
      "layer": "US", 
      "type": "Feature", 
      "properties": {
        "description": "", 
        "name": "Evanston Go club"
      }
    }, 
    {
      "geometry": {
        "type": "Point", 
        "coordinates": [
          -122.27924392945, 
          37.8744356684629
        ]
      }, 
      "layer": "US", 
      "type": "Feature", 
      "properties": {
        "description": "http://www.berkeleygoclub.org/ , Games of Berkeley, 2151 Shattuck Avenue, Berkeley in the center of the store on Mondays; in the downstairs game rooms at the same times on Thursday evenings , 6PM - 9 PM", 
        "name": "Games of Berkeley"
      }
    }, 
    {
      "geometry": {
        "type": "Point", 
        "coordinates": [
          -87.7178800106, 
          41.9214748362
        ]
      }, 
      "layer": "US", 
      "type": "Feature", 
      "properties": {
        "_storage_options": {
          "iconClass": "Ball"
        }, 
        "description": "", 
        "name": "Harridan Go Club (unofficial)"
      }
    }, 
    {
      "geometry": {
        "type": "Point", 
        "coordinates": [
          -121.935830788418, 
          37.3569764807581
        ]
      }, 
      "layer": "US", 
      "type": "Feature", 
      "properties": {
        "description": "http://www.meetup.com/GameKastleGoClub/ , Game Kastle, 1350 Coleman Ave, Santa Clara, CA , Saturdays: 1:00 pm to 3:00 pm; Please check website, as some holidays we may not meet. , Tom S. (Organizer) http://www.meetup.com/GameKastleGoClub/members/186613133/ , and Dave W. (Assistant Organizer) http://www.meetup.com/GameKastleGoClub/members/197276756/", 
        "name": "Kastle Go Club"
      }
    }, 
    {
      "geometry": {
        "type": "Point", 
        "coordinates": [
          -121.7697841, 
          37.6811682
        ]
      }, 
      "layer": "US", 
      "type": "Feature", 
      "properties": {
        "description": "Panama Red Coffee Co.\r\n2115 First Street, Livermore, CA , First and third Saturdays: 2:00 pm onward , Lynda L. LoDestro - lodestro1@llnl.gov", 
        "name": "Livermore Go Club"
      }
    }, 
    {
      "geometry": {
        "type": "Point", 
        "coordinates": [
          -122.143827964942, 
          37.4270298
        ]
      }, 
      "layer": "US", 
      "type": "Feature", 
      "properties": {
        "description": "http://www.mayfieldgoclub.com/ , Antonio's Nut House, 321 S. California Avenue, Palo Alto, CA , Wednesdays: 8:30 pm onward , http://mayfieldgoclub.com/contact/", 
        "name": "Mayfield Go Club"
      }
    }, 
    {
      "geometry": {
        "type": "Point", 
        "coordinates": [
          -122.267143315789, 
          37.8191727368421
        ]
      }, 
      "layer": "US", 
      "type": "Feature", 
      "properties": {
        "description": "http://www.meetup.com/North-Oakland-Go-Club/ , Black Spring Coffee Co., 2930 Telegraph Avenue, Oakland, CA , Sundays: 10:00 am to 5:00 pm , Tom S. http://www.meetup.com/North-Oakland-Go-Club/members/186613133/", 
        "name": "North Oakland Go Club"
      }
    }, 
    {
      "geometry": {
        "type": "Point", 
        "coordinates": [
          -122.274594478261, 
          37.8015712826087
        ]
      }, 
      "layer": "US", 
      "type": "Feature", 
      "properties": {
        "description": "http://www.meetup.com/North-Oakland-Go-Club/ , Endgame Cafe, 917 Washington St. (@10th St.) Oakland, CA , Tuesdays: 7:00 pm to 10:00 pm", 
        "name": "North Oakland Go Club at Endgame"
      }
    }, 
    {
      "geometry": {
        "type": "Point", 
        "coordinates": [
          -122.1872249, 
          37.4507104
        ]
      }, 
      "layer": "US", 
      "type": "Feature", 
      "properties": {
        "description": "Ing Goe Foundation, \r\n887 Oak Grove Road, Suite 203\r\nMenlo Park, CA , Saturdays: 1:00 pm to 4:00 pm,\r\nThe club is open Wednesday evenings from 8:00 pm for a free game review session with Mingjiu Jiang 7P", 
        "name": "Palo Alto Go Club"
      }
    }, 
    {
      "geometry": {
        "type": "Point", 
        "coordinates": [
          -112.045117191444, 
          33.5079157799959
        ]
      }, 
      "layer": "US", 
      "type": "Feature", 
      "properties": {
        "description": "https://www.facebook.com/Phoenixgoclub/ , Duck and Decanter\r\n1651 E Camelback Road\r\nPhoenix, AZ 85016 , Every other Sunday 1pm , Contact through Facebook", 
        "name": "Phoenixgoclub"
      }
    }, 
    {
      "geometry": {
        "type": "Point", 
        "coordinates": [
          -86.6263974357, 
          34.7120213385
        ]
      }, 
      "layer": "US", 
      "type": "Feature", 
      "properties": {
        "description": "Patton Rd, Huntsville AL , Noon-4 PM , http://www.facebook.com/groups/rocketcitygo\r\nemail: chonas009@hotmail.com", 
        "name": "Rocket City Go Club"
      }
    }, 
    {
      "geometry": {
        "type": "Point", 
        "coordinates": [
          -121.426803193663, 
          38.6012558633896
        ]
      }, 
      "layer": "US", 
      "type": "Feature", 
      "properties": {
        "description": "http://www.davissacramentogoclub.org , Market Square at Arden Fair in the Food Court near the Barnes and Noble Bookstore, 1725 Arden Way, Sacramento, CA , Mondays from 6-10pm", 
        "name": "Sacramento go club"
      }
    }, 
    {
      "geometry": {
        "type": "Point", 
        "coordinates": [
          -122.429100285714, 
          37.788611244898
        ]
      }, 
      "layer": "US", 
      "type": "Feature", 
      "properties": {
        "description": "http://www.sfgoclub.com , Nichiren Hokke Buddhist Church\r\n2016 Pine Street (near Laguna)\r\nSan Francisco, CA , Thursdays: 7:00 pm to 10:00 pm\r\nSundays: 1:00 pm to 5:30 pm\r\nThe club is only open on certain Thursdays and Sundays. Please check club website for exceptions to the normal schedule. , https://www.facebook.com/sfgoclub/", 
        "name": "San Francisco Go Club"
      }
    }, 
    {
      "geometry": {
        "type": "Point", 
        "coordinates": [
          -121.995764595386, 
          37.323042606557
        ]
      }, 
      "layer": "US", 
      "type": "Feature", 
      "properties": {
        "description": "http://www.gohappycup.com/club-when-where.shtml , Close to Stevens Creek Blvd & Lawrence Expressway, Santa Clara, CA. , Saturdays: 7:00 pm to 9:00 pm. Every child is welcome, even if you don't know how to play Go! , yanp.zhao@gmail.com", 
        "name": "Santa Clara Youth Go Club"
      }
    }, 
    {
      "geometry": {
        "type": "Point", 
        "coordinates": [
          -88.0342, 
          42.0405
        ]
      }, 
      "layer": "US", 
      "type": "Feature", 
      "properties": {
        "description": "http://schaumburggoclub.org/ , Starbucks (Sts of Woodfield)\r\n601 N Martingale Road\r\nSchaumburg, IL , Thursday 6:30-10:30 PM", 
        "name": "Schamburg Go Club"
      }
    }, 
    {
      "geometry": {
        "type": "Point", 
        "coordinates": [
          -77.8597855568, 
          40.7933274655
        ]
      }, 
      "layer": "US", 
      "type": "Feature", 
      "properties": {
        "description": "Musser Room (we share with the Chess Club) , every Saturday 14:00 , schlowgo@gmail.com", 
        "name": "Schlow Library Go Club"
      }
    }, 
    {
      "geometry": {
        "type": "Point", 
        "coordinates": [
          -122.048601512496, 
          37.241178431825
        ]
      }, 
      "layer": "US", 
      "type": "Feature", 
      "properties": {
        "description": "https://silivalleygoclub.wordpress.com/ , 15555 Bohlman Rd, Saratoga , We meet in Saratoga almost every Tuesday evening at 7:30. I send out an email every Monday to verify or cancel the club, but there are very few cancellations. Fill out the contact form on the website to be added to the mailing list.", 
        "name": "SiliValley Go Club"
      }
    }, 
    {
      "geometry": {
        "type": "Point", 
        "coordinates": [
          -122.718181995147, 
          38.3485916132
        ]
      }, 
      "layer": "US", 
      "type": "Feature", 
      "properties": {
        "description": "Sonoma Valley Bagel & Cafe, 350 Rohnert Park Expressway, Rohnert Park, CA , Sundays: 10:30 am to 4:00 pm , Contact Joanne and Ned Phipps 707-585-0669", 
        "name": "Sonoma County Go Club"
      }
    }, 
    {
      "geometry": {
        "type": "Point", 
        "coordinates": [
          -122.170810245751, 
          37.42421595
        ]
      }, 
      "layer": "US", 
      "type": "Feature", 
      "properties": {
        "description": "http://web.stanford.edu/group/go/ , Tresidder Union, 59 Lagunita Dr.\r\nStanford University, Stanford, CA , Sundays: 2:00 to 4:00 pm when school is in session , Active mailing list at https://mailman.stanford.edu/pipermail/go-club-chat/", 
        "name": "Stanford University Cardinal Go Club"
      }
    }, 
    {
      "geometry": {
        "type": "Point", 
        "coordinates": [
          -82.5732421875, 
          28.0525908233
        ]
      }, 
      "layer": "US", 
      "type": "Feature", 
      "properties": {
        "description": "https://www.facebook.com/tampagoclub/ , Saturdays , http://www.meetup.com/Tampa-Bay-Go-Baduk-Players/", 
        "name": "Tampa Go Club"
      }
    }, 
    {
      "geometry": {
        "type": "Point", 
        "coordinates": [
          -110.8632228, 
          32.221633125
        ]
      }, 
      "layer": "US", 
      "type": "Feature", 
      "properties": {
        "description": "https://www.facebook.com/groups/4616488521/ , Panera Bread, 6129 E Broadway Blvd, Tucson, AZ , Sundays starting between 4pm and 5pm and going till the place closes around 8pm. , Martin Lebl \r\nChapter Representative\r\n520-850-9213 martinlebl@gmail.com", 
        "name": "Tucson"
      }
    }, 
    {
      "geometry": {
        "type": "Point", 
        "coordinates": [
          -93.2877659798, 
          44.9521573692
        ]
      }, 
      "layer": "US", 
      "type": "Feature", 
      "properties": {
        "description": "Bob's Java Hut, 2651 Lyndale Ave S, Minneapolis, MN 55408 , Mondays, 18:00-23:00 , 612-871-4485", 
        "name": "Twin Cities Go Club (Monday)"
      }
    }, 
    {
      "geometry": {
        "type": "Point", 
        "coordinates": [
          -93.18775177, 
          44.9397114784
        ]
      }, 
      "layer": "US", 
      "type": "Feature", 
      "properties": {
        "description": "Coffee Bene, 53 Cleveland Avenue South, Saint Paul, MN 55105 , Saturdays, 13:00-17:00 , 651-698-2266", 
        "name": "Twin Cities Go Club (Saturday)"
      }
    }, 
    {
      "geometry": {
        "type": "Point", 
        "coordinates": [
          -93.2461702824, 
          44.9694055383
        ]
      }, 
      "layer": "US", 
      "type": "Feature", 
      "properties": {
        "description": "Hard Times Cafe, 1821 Riverside Avenue, Minneapolis, MN 55454-1034 , Thursdays 18:30-22:00", 
        "name": "Twin Cities Go Club (Thursday)"
      }
    }, 
    {
      "geometry": {
        "type": "Point", 
        "coordinates": [
          -123.348098271844, 
          39.3906947307103
        ]
      }, 
      "layer": "US", 
      "type": "Feature", 
      "properties": {
        "description": "Super Taco - Evergreen Shopping Center, 1726 S Main St. #A, Willits, CA , Tuesdays: 6:00 to 9:00 pm , Contact Brian Ferri-Taylor 707-459-9628", 
        "name": "Willits Go Club"
      }
    }
  ]
}